[{"__type__":"cc.SpriteFrame","content":{"name":"successful","texture":"00EWm4W/JDr4XoQLmK1RR1","rect":[0,0,560,603],"offset":[0,0],"originalSize":[560,603]}},{"__type__":"cc.SpriteFrame","content":{"name":"button-hover","texture":"c8GDCOehdAOIbbMFl9PneJ","rect":[0,0,206,64],"offset":[0,0],"originalSize":[206,64]}},{"__type__":"cc.SpriteFrame","content":{"name":"singleColor","texture":"a8Anh32NZGRZegUtSgEj26","rect":[0,0,2,2],"offset":[0,0],"originalSize":[2,2]}},{"__type__":"cc.SpriteFrame","content":{"name":"failed","texture":"e6RxW3CMlFmYNxKak7y6Gn","rect":[0,7,529,546],"offset":[0,-3.5],"originalSize":[529,553]}},{"__type__":"cc.SpriteFrame","content":{"name":"background","texture":"b4cxlp0nRJiZo5W3QJgx0y","rect":[0,0,492,483],"offset":[0,0],"originalSize":[492,483]}},{"__type__":"cc.SpriteFrame","content":{"name":"button","texture":"fcXaVcZO5IdoiYIcUF7FRe","rect":[0,0,206,64],"offset":[0,0],"originalSize":[206,64]}},{"__type__":"cc.SpriteFrame","content":{"name":"title-background","texture":"10Km8zbZdMxaI0g89w4kIa","rect":[0,0,498,157],"offset":[0,0],"originalSize":[498,157]}},[{"__type__":"cc.Prefab","_name":"LayerResult_Red","data":{"__id__":1}},{"__type__":"cc.Node","_name":"LayerResult_Red","_children":[{"__id__":2},{"__id__":3},{"__id__":38}],"_level":2,"_components":[{"__type__":"cc.Widget","node":{"__id__":1},"_alignFlags":45},{"__type__":"d6efbdphsFKDr3o1qugPf1F","node":{"__id__":1},"successLayer":{"__id__":3},"failedLayer":{"__id__":38},"_result":""},{"__type__":"cc.Button","node":{"__id__":1},"_N$target":{"__id__":1}}],"_prefab":{"__type__":"cc.PrefabInfo","root":{"__id__":1},"asset":{"__uuid__":"f9E3S/NllC/5TspXPap7Bo"},"fileId":"86qObioflAHoZRTohtqVWY"},"_contentSize":{"__type__":"cc.Size","width":640,"height":1013},"_scale":{"__type__":"cc.Vec3","x":1,"y":1,"z":1}},{"__type__":"cc.Node","_name":"Layer","_parent":{"__id__":1},"_level":3,"_components":[{"__type__":"cc.Sprite","node":{"__id__":2},"_spriteFrame":{"__uuid__":"9bvaMerUlDyary99mJa6xp"},"_type":1,"_sizeMode":0},{"__type__":"cc.Layout","node":{"__id__":2},"_layoutSize":{"__type__":"cc.Size","width":640,"height":1013}},{"__type__":"cc.Widget","node":{"__id__":2},"_alignFlags":45,"_originalWidth":200,"_originalHeight":150}],"_prefab":{"__type__":"cc.PrefabInfo","root":{"__id__":1},"asset":{"__uuid__":"f9E3S/NllC/5TspXPap7Bo"},"fileId":"f7AxfgcBhIcYbXvNlZm4OL"},"_opacity":200,"_color":{"__type__":"cc.Color"},"_contentSize":{"__type__":"cc.Size","width":640,"height":1013},"_scale":{"__type__":"cc.Vec3","x":1,"y":1,"z":1}},{"__type__":"cc.Node","_name":"Successful","_parent":{"__id__":1},"_children":[{"__id__":4},{"__id__":11},{"__id__":37}],"_active":false,"_level":3,"_components":[{"__type__":"cc.Widget","node":{"__id__":3},"_alignFlags":45}],"_prefab":{"__type__":"cc.PrefabInfo","root":{"__id__":1},"asset":{"__uuid__":"f9E3S/NllC/5TspXPap7Bo"},"fileId":"13MF/F1lFNzIaJSTKb0RDS"},"_contentSize":{"__type__":"cc.Size","width":640,"height":1013},"_scale":{"__type__":"cc.Vec3","x":1,"y":1,"z":1}},{"__type__":"cc.Node","_name":"Buttons","_parent":{"__id__":3},"_children":[{"__id__":5},{"__id__":7},{"__id__":9}],"_level":4,"_components":[{"__type__":"cc.Layout","node":{"__id__":4},"_layoutSize":{"__type__":"cc.Size","width":432,"height":200},"_resize":1,"_N$layoutType":1,"_N$spacingX":20},{"__type__":"cc.Widget","node":{"__id__":4},"_alignFlags":16,"_left":170,"_right":170,"_originalWidth":300}],"_prefab":{"__type__":"cc.PrefabInfo","root":{"__id__":1},"asset":{"__uuid__":"f9E3S/NllC/5TspXPap7Bo"},"fileId":"6cT+pDdl9BLI7fJ//Nv/8o"},"_contentSize":{"__type__":"cc.Size","width":432,"height":200},"_scale":{"__type__":"cc.Vec3","x":1,"y":1,"z":1}},{"__type__":"cc.Node","_name":"Subscribe","_parent":{"__id__":4},"_children":[{"__id__":6}],"_active":false,"_level":5,"_components":[{"__type__":"cc.Sprite","node":{"__id__":5},"_spriteFrame":{"__uuid__":"edRXsXSUVJja1zANb/8hDQ"}},{"__type__":"cc.Button","node":{"__id__":5},"transition":2,"pressedColor":{"__type__":"cc.Color","r":255,"g":255,"b":255},"clickEvents":[{"__type__":"cc.ClickEvent","target":{"__id__":1},"component":"LayerResult","handler":"btnAction","customEventData":"subscribe"}],"_N$normalColor":{"__type__":"cc.Color","r":255,"g":255,"b":255},"_N$disabledColor":{"__type__":"cc.Color","r":255,"g":255,"b":255},"_N$normalSprite":{"__uuid__":"edRXsXSUVJja1zANb/8hDQ"},"_N$pressedSprite":{"__uuid__":"26iqIqvGxP1rGL1GKtpmX/"},"pressedSprite":{"__uuid__":"26iqIqvGxP1rGL1GKtpmX/"},"_N$hoverSprite":{"__uuid__":"edRXsXSUVJja1zANb/8hDQ"},"hoverSprite":{"__uuid__":"edRXsXSUVJja1zANb/8hDQ"},"_N$disabledSprite":{"__uuid__":"edRXsXSUVJja1zANb/8hDQ"},"_N$target":{"__id__":5}},{"__type__":"cc.Widget","node":{"__id__":5},"_alignFlags":2,"_left":200,"_right":-50,"_verticalCenter":-400,"_horizontalCenter":150,"_originalWidth":200}],"_prefab":{"__type__":"cc.PrefabInfo","root":{"__id__":1},"asset":{"__uuid__":"f9E3S/NllC/5TspXPap7Bo"},"fileId":"85ujhJQqlKNZk+cevQy++n"},"_contentSize":{"__type__":"cc.Size","width":206,"height":64},"_position":{"__type__":"cc.Vec3","x":-226,"y":-400},"_scale":{"__type__":"cc.Vec3","x":1,"y":1,"z":1}},{"__type__":"cc.Node","_name":"Label","_parent":{"__id__":5},"_components":[{"__type__":"cc.Label","node":{"__id__":6},"_srcBlendFactor":1,"_useOriginalSize":false,"_string":"关注我们","_N$string":"关注我们","_fontSize":26,"_enableWrapText":false,"_N$horizontalAlign":1,"_N$verticalAlign":1,"_N$fontFamily":"Microsoft YaHei","_N$overflow":1}],"_prefab":{"__type__":"cc.PrefabInfo","root":{"__id__":1},"asset":{"__uuid__":"f9E3S/NllC/5TspXPap7Bo"},"fileId":"5bDjZoz5hGk5D1k82lTCPb"},"_contentSize":{"__type__":"cc.Size","width":160,"height":40},"_scale":{"__type__":"cc.Vec3","x":1,"y":1,"z":1}},{"__type__":"cc.Node","_name":"Return","_parent":{"__id__":4},"_children":[{"__id__":8}],"_level":5,"_components":[{"__type__":"cc.Sprite","node":{"__id__":7},"_spriteFrame":{"__uuid__":"edRXsXSUVJja1zANb/8hDQ"}},{"__type__":"cc.Button","node":{"__id__":7},"transition":2,"pressedColor":{"__type__":"cc.Color","r":255,"g":255,"b":255},"clickEvents":[{"__type__":"cc.ClickEvent","target":{"__id__":1},"component":"LayerResult","handler":"btnAction","customEventData":"return"}],"_N$normalColor":{"__type__":"cc.Color","r":255,"g":255,"b":255},"_N$disabledColor":{"__type__":"cc.Color","r":255,"g":255,"b":255},"_N$normalSprite":{"__uuid__":"edRXsXSUVJja1zANb/8hDQ"},"_N$pressedSprite":{"__uuid__":"26iqIqvGxP1rGL1GKtpmX/"},"pressedSprite":{"__uuid__":"26iqIqvGxP1rGL1GKtpmX/"},"_N$hoverSprite":{"__uuid__":"edRXsXSUVJja1zANb/8hDQ"},"hoverSprite":{"__uuid__":"edRXsXSUVJja1zANb/8hDQ"},"_N$disabledSprite":{"__uuid__":"edRXsXSUVJja1zANb/8hDQ"},"_N$target":{"__id__":7}},{"__type__":"cc.Widget","node":{"__id__":7},"_alignFlags":2,"_left":200,"_right":-50,"_verticalCenter":-400,"_horizontalCenter":150,"_originalWidth":200}],"_prefab":{"__type__":"cc.PrefabInfo","root":{"__id__":1},"asset":{"__uuid__":"f9E3S/NllC/5TspXPap7Bo"},"fileId":"148Hh4t+NGD71KIfPvq+c3"},"_contentSize":{"__type__":"cc.Size","width":206,"height":64},"_position":{"__type__":"cc.Vec3","x":-113,"y":-400},"_scale":{"__type__":"cc.Vec3","x":1,"y":1,"z":1}},{"__type__":"cc.Node","_name":"Label","_parent":{"__id__":7},"_components":[{"__type__":"cc.Label","node":{"__id__":8},"_srcBlendFactor":1,"_useOriginalSize":false,"_string":"返回首页","_N$string":"返回首页","_fontSize":26,"_enableWrapText":false,"_N$horizontalAlign":1,"_N$verticalAlign":1,"_N$fontFamily":"Microsoft YaHei","_N$overflow":1}],"_prefab":{"__type__":"cc.PrefabInfo","root":{"__id__":1},"asset":{"__uuid__":"f9E3S/NllC/5TspXPap7Bo"},"fileId":"74uQP34cpEt6fxGXirZ5EO"},"_contentSize":{"__type__":"cc.Size","width":160,"height":40},"_scale":{"__type__":"cc.Vec3","x":1,"y":1,"z":1}},{"__type__":"cc.Node","_name":"Submit","_parent":{"__id__":4},"_children":[{"__id__":10}],"_level":5,"_components":[{"__type__":"cc.Sprite","node":{"__id__":9},"_spriteFrame":{"__uuid__":"edRXsXSUVJja1zANb/8hDQ"}},{"__type__":"cc.Button","node":{"__id__":9},"transition":2,"pressedColor":{"__type__":"cc.Color","r":255,"g":255,"b":255},"clickEvents":[{"__type__":"cc.ClickEvent","target":{"__id__":1},"component":"LayerResult","handler":"btnAction","customEventData":"submit"}],"_N$normalColor":{"__type__":"cc.Color","r":255,"g":255,"b":255},"_N$disabledColor":{"__type__":"cc.Color","r":255,"g":255,"b":255},"_N$normalSprite":{"__uuid__":"edRXsXSUVJja1zANb/8hDQ"},"_N$pressedSprite":{"__uuid__":"26iqIqvGxP1rGL1GKtpmX/"},"pressedSprite":{"__uuid__":"26iqIqvGxP1rGL1GKtpmX/"},"_N$hoverSprite":{"__uuid__":"edRXsXSUVJja1zANb/8hDQ"},"hoverSprite":{"__uuid__":"edRXsXSUVJja1zANb/8hDQ"},"_N$disabledSprite":{"__uuid__":"edRXsXSUVJja1zANb/8hDQ"},"_N$target":{"__id__":9}},{"__type__":"cc.Widget","node":{"__id__":9},"_alignFlags":2,"_left":200,"_right":-50,"_verticalCenter":-400,"_horizontalCenter":150,"_originalWidth":200}],"_prefab":{"__type__":"cc.PrefabInfo","root":{"__id__":1},"asset":{"__uuid__":"f9E3S/NllC/5TspXPap7Bo"},"fileId":"a5stL8dI9Nzpk3TU2aj+2S"},"_contentSize":{"__type__":"cc.Size","width":206,"height":64},"_position":{"__type__":"cc.Vec3","x":113,"y":-400},"_scale":{"__type__":"cc.Vec3","x":1,"y":1,"z":1}},{"__type__":"cc.Node","_name":"Label","_parent":{"__id__":9},"_components":[{"__type__":"cc.Label","node":{"__id__":10},"_srcBlendFactor":1,"_useOriginalSize":false,"_string":"提交信息","_N$string":"提交信息","_fontSize":26,"_enableWrapText":false,"_N$horizontalAlign":1,"_N$verticalAlign":1,"_N$fontFamily":"Microsoft YaHei","_N$overflow":1}],"_prefab":{"__type__":"cc.PrefabInfo","root":{"__id__":1},"asset":{"__uuid__":"f9E3S/NllC/5TspXPap7Bo"},"fileId":"97lA6mP0lDrIvPL/oxf6JC"},"_contentSize":{"__type__":"cc.Size","width":160,"height":40},"_scale":{"__type__":"cc.Vec3","x":1,"y":1,"z":1}},{"__type__":"cc.Node","_name":"Body","_parent":{"__id__":3},"_children":[{"__id__":12},{"__id__":35}],"_level":4,"_components":[{"__type__":"cc.Widget","node":{"__id__":11},"_alignFlags":18,"_verticalCenter":-80}],"_prefab":{"__type__":"cc.PrefabInfo","root":{"__id__":1},"asset":{"__uuid__":"f9E3S/NllC/5TspXPap7Bo"},"fileId":"89B7Kl6F5OSIbjX3/N9qG5"},"_position":{"__type__":"cc.Vec3","y":-80},"_scale":{"__type__":"cc.Vec3","x":1,"y":1,"z":1}},{"__type__":"cc.Node","_name":"Desc","_parent":{"__id__":11},"_children":[{"__id__":13}],"_level":5,"_components":[{"__type__":"cc.Sprite","node":{"__id__":12},"_spriteFrame":{"__uuid__":"98cEIeb99A1JtBYBZYS35d"}}],"_prefab":{"__type__":"cc.PrefabInfo","root":{"__id__":1},"asset":{"__uuid__":"f9E3S/NllC/5TspXPap7Bo"},"fileId":"8czGURldxHWZPFhDgh5no2"},"_contentSize":{"__type__":"cc.Size","width":492,"height":483},"_scale":{"__type__":"cc.Vec3","x":1,"y":1,"z":1}},{"__type__":"cc.Node","_name":"Form","_parent":{"__id__":12},"_children":[{"__id__":14},{"__id__":21},{"__id__":28}],"_level":6,"_components":[{"__type__":"cc.Widget","node":{"__id__":13},"_alignFlags":45,"_left":30,"_right":30,"_top":181.5,"_bottom":61.5},{"__type__":"cc.Layout","node":{"__id__":13},"_layoutSize":{"__type__":"cc.Size","width":432,"height":240},"_resize":1,"_N$layoutType":2,"_N$paddingTop":20,"_N$paddingBottom":20,"_N$spacingY":40}],"_prefab":{"__type__":"cc.PrefabInfo","root":{"__id__":1},"asset":{"__uuid__":"f9E3S/NllC/5TspXPap7Bo"},"fileId":"0f/0QkNhdLrowGnDpKn5gw"},"_contentSize":{"__type__":"cc.Size","width":432,"height":240},"_position":{"__type__":"cc.Vec3","y":-60},"_scale":{"__type__":"cc.Vec3","x":1,"y":1,"z":1}},{"__type__":"cc.Node","_name":"Row","_parent":{"__id__":13},"_children":[{"__id__":15},{"__id__":16}],"_level":7,"_components":[{"__type__":"cc.Widget","node":{"__id__":14},"_alignFlags":16}],"_prefab":{"__type__":"cc.PrefabInfo","root":{"__id__":1},"asset":{"__uuid__":"f9E3S/NllC/5TspXPap7Bo"},"fileId":"10Po0OuZBHeorx2AbWMtAu"},"_contentSize":{"__type__":"cc.Size","width":400,"height":40},"_position":{"__type__":"cc.Vec3","y":80},"_scale":{"__type__":"cc.Vec3","x":1,"y":1,"z":1}},{"__type__":"cc.Node","_name":"Label","_parent":{"__id__":14},"_level":8,"_components":[{"__type__":"cc.Label","node":{"__id__":15},"_srcBlendFactor":1,"_useOriginalSize":false,"_string":"收件人：","_N$string":"收件人：","_fontSize":24,"_N$horizontalAlign":2,"_N$verticalAlign":1,"_N$fontFamily":"Microsoft YaHei","_N$overflow":2},{"__type__":"cc.Widget","node":{"__id__":15},"_alignFlags":10,"_right":264,"_originalWidth":96}],"_prefab":{"__type__":"cc.PrefabInfo","root":{"__id__":1},"asset":{"__uuid__":"f9E3S/NllC/5TspXPap7Bo"},"fileId":"9fgv5O7HhOnoUm3Rj2eg92"},"_color":{"__type__":"cc.Color","r":254,"g":68,"b":41},"_contentSize":{"__type__":"cc.Size","width":100,"height":40},"_position":{"__type__":"cc.Vec3","x":-150},"_scale":{"__type__":"cc.Vec3","x":1,"y":1,"z":1}},{"__type__":"cc.Node","_name":"Input","_parent":{"__id__":14},"_children":[{"__id__":17},{"__id__":18},{"__id__":19},{"__id__":20}],"_level":8,"_components":[{"__type__":"cc.EditBox","node":{"__id__":16},"_useOriginalSize":false,"_N$backgroundImage":{"__uuid__":"ffDpHHVcZAhqOfy25Fe4w7"},"_N$inputMode":6,"_N$fontSize":24,"_N$fontColor":{"__type__":"cc.Color","r":254,"g":68,"b":41},"_N$placeholder":"","_N$placeholderFontColor":{"__type__":"cc.Color","r":187,"g":187,"b":187},"_N$maxLength":8},{"__type__":"cc.Widget","node":{"__id__":16},"_alignFlags":42,"_left":100,"_right":10,"_originalWidth":200}],"_prefab":{"__type__":"cc.PrefabInfo","root":{"__id__":1},"asset":{"__uuid__":"f9E3S/NllC/5TspXPap7Bo"},"fileId":"6dvfofgXFP54gb2HjCdKfe"},"_contentSize":{"__type__":"cc.Size","width":290,"height":40},"_position":{"__type__":"cc.Vec3","x":45},"_scale":{"__type__":"cc.Vec3","x":1,"y":1,"z":1}},{"__type__":"cc.Node","_name":"BACKGROUND_SPRITE_CUSTOM","_parent":{"__id__":16},"_level":9,"_components":[{"__type__":"cc.Sprite","node":{"__id__":17},"_spriteFrame":{"__uuid__":"41D7kWhyFGY7q4NDlzkazn"},"_type":1,"_sizeMode":0},{"__type__":"cc.Widget","node":{"__id__":17},"_alignFlags":45,"_top":38,"_verticalCenter":-14,"_originalWidth":160,"_originalHeight":2}],"_prefab":{"__type__":"cc.PrefabInfo","root":{"__id__":1},"asset":{"__uuid__":"f9E3S/NllC/5TspXPap7Bo"},"fileId":"89zSEYLLxKp5w9T0SQOzV6"},"_color":{"__type__":"cc.Color","r":254,"g":68,"b":41},"_contentSize":{"__type__":"cc.Size","width":290,"height":2},"_position":{"__type__":"cc.Vec3","y":-19},"_scale":{"__type__":"cc.Vec3","x":1,"y":1,"z":1}},{"__type__":"cc.Node","_name":"BACKGROUND_SPRITE","_parent":{"__id__":16},"_active":false,"_level":9,"_components":[{"__type__":"cc.Sprite","node":{"__id__":18},"_spriteFrame":{"__uuid__":"ffDpHHVcZAhqOfy25Fe4w7"},"_type":1,"_sizeMode":0},{"__type__":"cc.Widget","node":{"__id__":18},"_alignFlags":42,"_verticalCenter":-14,"_originalWidth":160}],"_prefab":{"__type__":"cc.PrefabInfo","root":{"__id__":1},"asset":{"__uuid__":"f9E3S/NllC/5TspXPap7Bo"},"fileId":"a5eHJtu8dOhLyXxg4XSSog"},"_color":{"__type__":"cc.Color","r":254,"g":68,"b":41},"_contentSize":{"__type__":"cc.Size","width":290,"height":40},"_position":{"__type__":"cc.Vec3","y":-14},"_scale":{"__type__":"cc.Vec3","x":1,"y":1,"z":1}},{"__type__":"cc.Node","_name":"TEXT_LABEL","_parent":{"__id__":16},"_active":false,"_level":2,"_components":[{"__type__":"cc.Label","node":{"__id__":19},"_srcBlendFactor":1,"_fontSize":24,"_enableWrapText":false,"_N$verticalAlign":1,"_N$fontFamily":"Microsoft YaHei","_N$overflow":1},{"__type__":"cc.Widget","node":{"__id__":19},"_alignFlags":42,"_originalWidth":158}],"_prefab":{"__type__":"cc.PrefabInfo","root":{"__id__":1},"asset":{"__uuid__":"f9E3S/NllC/5TspXPap7Bo"},"fileId":"beRlqnj65MV7aW+XNsaTmY"},"_color":{"__type__":"cc.Color","r":254,"g":68,"b":41},"_contentSize":{"__type__":"cc.Size","width":288,"height":40},"_anchorPoint":{"__type__":"cc.Vec2","y":1},"_position":{"__type__":"cc.Vec3","x":-143,"y":20},"_scale":{"__type__":"cc.Vec3","x":1,"y":1,"z":1}},{"__type__":"cc.Node","_name":"PLACEHOLDER_LABEL","_parent":{"__id__":16},"_level":2,"_components":[{"__type__":"cc.Label","node":{"__id__":20},"_srcBlendFactor":1,"_fontSize":20,"_enableWrapText":false,"_N$verticalAlign":1,"_N$fontFamily":"Microsoft YaHei","_N$overflow":1},{"__type__":"cc.Widget","node":{"__id__":20},"_alignFlags":42,"_originalWidth":158}],"_prefab":{"__type__":"cc.PrefabInfo","root":{"__id__":1},"asset":{"__uuid__":"f9E3S/NllC/5TspXPap7Bo"},"fileId":"2dS5oihe1Eg6xwRiXpMVZQ"},"_color":{"__type__":"cc.Color","r":187,"g":187,"b":187},"_contentSize":{"__type__":"cc.Size","width":290,"height":40},"_anchorPoint":{"__type__":"cc.Vec2","y":1},"_position":{"__type__":"cc.Vec3","x":-145,"y":20},"_scale":{"__type__":"cc.Vec3","x":1,"y":1,"z":1}},{"__type__":"cc.Node","_name":"Row","_parent":{"__id__":13},"_children":[{"__id__":22},{"__id__":23}],"_level":7,"_components":[{"__type__":"cc.Widget","node":{"__id__":21},"_alignFlags":16}],"_prefab":{"__type__":"cc.PrefabInfo","root":{"__id__":1},"asset":{"__uuid__":"f9E3S/NllC/5TspXPap7Bo"},"fileId":"9ffRxQI01H5pnyWrdbb6mJ"},"_contentSize":{"__type__":"cc.Size","width":400,"height":40},"_scale":{"__type__":"cc.Vec3","x":1,"y":1,"z":1}},{"__type__":"cc.Node","_name":"Label","_parent":{"__id__":21},"_level":8,"_components":[{"__type__":"cc.Label","node":{"__id__":22},"_srcBlendFactor":1,"_useOriginalSize":false,"_string":"电话：","_N$string":"电话：","_fontSize":24,"_N$horizontalAlign":2,"_N$verticalAlign":1,"_N$fontFamily":"Microsoft YaHei","_N$overflow":2},{"__type__":"cc.Widget","node":{"__id__":22},"_alignFlags":10,"_right":264,"_originalWidth":96}],"_prefab":{"__type__":"cc.PrefabInfo","root":{"__id__":1},"asset":{"__uuid__":"f9E3S/NllC/5TspXPap7Bo"},"fileId":"c3P/znAwBP+YpZZpqVTlGw"},"_color":{"__type__":"cc.Color","r":254,"g":68,"b":41},"_contentSize":{"__type__":"cc.Size","width":100,"height":40},"_position":{"__type__":"cc.Vec3","x":-150},"_scale":{"__type__":"cc.Vec3","x":1,"y":1,"z":1}},{"__type__":"cc.Node","_name":"Input","_parent":{"__id__":21},"_children":[{"__id__":24},{"__id__":25},{"__id__":26},{"__id__":27}],"_level":8,"_components":[{"__type__":"cc.EditBox","node":{"__id__":23},"_useOriginalSize":false,"_N$backgroundImage":{"__uuid__":"ffDpHHVcZAhqOfy25Fe4w7"},"_N$inputMode":6,"_N$fontSize":24,"_N$fontColor":{"__type__":"cc.Color","r":254,"g":68,"b":41},"_N$placeholder":"","_N$placeholderFontColor":{"__type__":"cc.Color","r":187,"g":187,"b":187},"_N$maxLength":11},{"__type__":"cc.Widget","node":{"__id__":23},"_alignFlags":42,"_left":100,"_right":10,"_originalWidth":200}],"_prefab":{"__type__":"cc.PrefabInfo","root":{"__id__":1},"asset":{"__uuid__":"f9E3S/NllC/5TspXPap7Bo"},"fileId":"c4uCrXOh1J3Lg+hkhdKPMe"},"_contentSize":{"__type__":"cc.Size","width":290,"height":40},"_position":{"__type__":"cc.Vec3","x":45},"_scale":{"__type__":"cc.Vec3","x":1,"y":1,"z":1}},{"__type__":"cc.Node","_name":"BACKGROUND_SPRITE_CUSTOM","_parent":{"__id__":23},"_level":9,"_components":[{"__type__":"cc.Sprite","node":{"__id__":24},"_spriteFrame":{"__uuid__":"41D7kWhyFGY7q4NDlzkazn"},"_type":1,"_sizeMode":0},{"__type__":"cc.Widget","node":{"__id__":24},"_alignFlags":45,"_top":38,"_verticalCenter":-14,"_originalWidth":160,"_originalHeight":2}],"_prefab":{"__type__":"cc.PrefabInfo","root":{"__id__":1},"asset":{"__uuid__":"f9E3S/NllC/5TspXPap7Bo"},"fileId":"40t7m6Qv9JHJdQ/FqQ9C7Q"},"_color":{"__type__":"cc.Color","r":254,"g":68,"b":41},"_contentSize":{"__type__":"cc.Size","width":290,"height":2},"_position":{"__type__":"cc.Vec3","y":-19},"_scale":{"__type__":"cc.Vec3","x":1,"y":1,"z":1}},{"__type__":"cc.Node","_name":"BACKGROUND_SPRITE","_parent":{"__id__":23},"_active":false,"_level":9,"_components":[{"__type__":"cc.Sprite","node":{"__id__":25},"_spriteFrame":{"__uuid__":"ffDpHHVcZAhqOfy25Fe4w7"},"_type":1,"_sizeMode":0},{"__type__":"cc.Widget","node":{"__id__":25},"_alignFlags":42,"_verticalCenter":-14,"_originalWidth":160}],"_prefab":{"__type__":"cc.PrefabInfo","root":{"__id__":1},"asset":{"__uuid__":"f9E3S/NllC/5TspXPap7Bo"},"fileId":"ceYyYnB4pJg5AF4ApfX3K4"},"_color":{"__type__":"cc.Color","r":254,"g":68,"b":41},"_contentSize":{"__type__":"cc.Size","width":290,"height":40},"_position":{"__type__":"cc.Vec3","y":-14},"_scale":{"__type__":"cc.Vec3","x":1,"y":1,"z":1}},{"__type__":"cc.Node","_name":"TEXT_LABEL","_parent":{"__id__":23},"_active":false,"_level":2,"_components":[{"__type__":"cc.Label","node":{"__id__":26},"_srcBlendFactor":1,"_fontSize":24,"_enableWrapText":false,"_N$verticalAlign":1,"_N$fontFamily":"Microsoft YaHei","_N$overflow":1},{"__type__":"cc.Widget","node":{"__id__":26},"_alignFlags":42,"_originalWidth":158}],"_prefab":{"__type__":"cc.PrefabInfo","root":{"__id__":1},"asset":{"__uuid__":"f9E3S/NllC/5TspXPap7Bo"},"fileId":"d0+WVJ8OxGyb1a/SbZJtwT"},"_color":{"__type__":"cc.Color","r":254,"g":68,"b":41},"_contentSize":{"__type__":"cc.Size","width":288,"height":40},"_anchorPoint":{"__type__":"cc.Vec2","y":1},"_position":{"__type__":"cc.Vec3","x":-143,"y":20},"_scale":{"__type__":"cc.Vec3","x":1,"y":1,"z":1}},{"__type__":"cc.Node","_name":"PLACEHOLDER_LABEL","_parent":{"__id__":23},"_level":2,"_components":[{"__type__":"cc.Label","node":{"__id__":27},"_srcBlendFactor":1,"_fontSize":20,"_enableWrapText":false,"_N$verticalAlign":1,"_N$fontFamily":"Microsoft YaHei","_N$overflow":1},{"__type__":"cc.Widget","node":{"__id__":27},"_alignFlags":42,"_originalWidth":158}],"_prefab":{"__type__":"cc.PrefabInfo","root":{"__id__":1},"asset":{"__uuid__":"f9E3S/NllC/5TspXPap7Bo"},"fileId":"c5I0nOoyJEM6odhTHzn68o"},"_color":{"__type__":"cc.Color","r":187,"g":187,"b":187},"_contentSize":{"__type__":"cc.Size","width":290,"height":40},"_anchorPoint":{"__type__":"cc.Vec2","y":1},"_position":{"__type__":"cc.Vec3","x":-145,"y":20},"_scale":{"__type__":"cc.Vec3","x":1,"y":1,"z":1}},{"__type__":"cc.Node","_name":"Row","_parent":{"__id__":13},"_children":[{"__id__":29},{"__id__":30}],"_level":7,"_components":[{"__type__":"cc.Widget","node":{"__id__":28},"_alignFlags":16}],"_prefab":{"__type__":"cc.PrefabInfo","root":{"__id__":1},"asset":{"__uuid__":"f9E3S/NllC/5TspXPap7Bo"},"fileId":"72MCJxgndNK5/azuP1l4wq"},"_contentSize":{"__type__":"cc.Size","width":400,"height":40},"_position":{"__type__":"cc.Vec3","y":-80},"_scale":{"__type__":"cc.Vec3","x":1,"y":1,"z":1}},{"__type__":"cc.Node","_name":"Label","_parent":{"__id__":28},"_level":8,"_components":[{"__type__":"cc.Label","node":{"__id__":29},"_srcBlendFactor":1,"_useOriginalSize":false,"_string":"地址：","_N$string":"地址：","_fontSize":24,"_N$horizontalAlign":2,"_N$verticalAlign":1,"_N$fontFamily":"Microsoft YaHei","_N$overflow":2},{"__type__":"cc.Widget","node":{"__id__":29},"_alignFlags":10,"_right":264,"_originalWidth":96}],"_prefab":{"__type__":"cc.PrefabInfo","root":{"__id__":1},"asset":{"__uuid__":"f9E3S/NllC/5TspXPap7Bo"},"fileId":"46q/zJZXNMvoVUXkvT/o0u"},"_color":{"__type__":"cc.Color","r":254,"g":68,"b":41},"_contentSize":{"__type__":"cc.Size","width":100,"height":40},"_position":{"__type__":"cc.Vec3","x":-150},"_scale":{"__type__":"cc.Vec3","x":1,"y":1,"z":1}},{"__type__":"cc.Node","_name":"Input","_parent":{"__id__":28},"_children":[{"__id__":31},{"__id__":32},{"__id__":33},{"__id__":34}],"_level":8,"_components":[{"__type__":"cc.EditBox","node":{"__id__":30},"_useOriginalSize":false,"_N$backgroundImage":{"__uuid__":"ffDpHHVcZAhqOfy25Fe4w7"},"_N$inputMode":6,"_N$fontSize":24,"_N$fontColor":{"__type__":"cc.Color","r":254,"g":68,"b":41},"_N$placeholder":"","_N$placeholderFontColor":{"__type__":"cc.Color","r":187,"g":187,"b":187},"_N$maxLength":50},{"__type__":"cc.Widget","node":{"__id__":30},"_alignFlags":42,"_left":100,"_right":10,"_originalWidth":200}],"_prefab":{"__type__":"cc.PrefabInfo","root":{"__id__":1},"asset":{"__uuid__":"f9E3S/NllC/5TspXPap7Bo"},"fileId":"a39lXb7YlG8rKTYuDN1WwW"},"_contentSize":{"__type__":"cc.Size","width":290,"height":40},"_position":{"__type__":"cc.Vec3","x":45},"_scale":{"__type__":"cc.Vec3","x":1,"y":1,"z":1}},{"__type__":"cc.Node","_name":"BACKGROUND_SPRITE_CUSTOM","_parent":{"__id__":30},"_level":9,"_components":[{"__type__":"cc.Sprite","node":{"__id__":31},"_spriteFrame":{"__uuid__":"41D7kWhyFGY7q4NDlzkazn"},"_type":1,"_sizeMode":0},{"__type__":"cc.Widget","node":{"__id__":31},"_alignFlags":45,"_top":38,"_verticalCenter":-14,"_originalWidth":160,"_originalHeight":2}],"_prefab":{"__type__":"cc.PrefabInfo","root":{"__id__":1},"asset":{"__uuid__":"f9E3S/NllC/5TspXPap7Bo"},"fileId":"6aHih5jztCwrdrSCncrTDp"},"_color":{"__type__":"cc.Color","r":254,"g":68,"b":41},"_contentSize":{"__type__":"cc.Size","width":290,"height":2},"_position":{"__type__":"cc.Vec3","y":-19},"_scale":{"__type__":"cc.Vec3","x":1,"y":1,"z":1}},{"__type__":"cc.Node","_name":"BACKGROUND_SPRITE","_parent":{"__id__":30},"_active":false,"_level":9,"_components":[{"__type__":"cc.Sprite","node":{"__id__":32},"_spriteFrame":{"__uuid__":"ffDpHHVcZAhqOfy25Fe4w7"},"_type":1,"_sizeMode":0},{"__type__":"cc.Widget","node":{"__id__":32},"_alignFlags":42,"_verticalCenter":-14,"_originalWidth":160}],"_prefab":{"__type__":"cc.PrefabInfo","root":{"__id__":1},"asset":{"__uuid__":"f9E3S/NllC/5TspXPap7Bo"},"fileId":"10nEyLbFFO7oAG9LLNvY6y"},"_color":{"__type__":"cc.Color","r":254,"g":68,"b":41},"_contentSize":{"__type__":"cc.Size","width":290,"height":40},"_position":{"__type__":"cc.Vec3","y":-14},"_scale":{"__type__":"cc.Vec3","x":1,"y":1,"z":1}},{"__type__":"cc.Node","_name":"TEXT_LABEL","_parent":{"__id__":30},"_active":false,"_level":2,"_components":[{"__type__":"cc.Label","node":{"__id__":33},"_srcBlendFactor":1,"_fontSize":24,"_enableWrapText":false,"_N$verticalAlign":1,"_N$fontFamily":"Microsoft YaHei","_N$overflow":1},{"__type__":"cc.Widget","node":{"__id__":33},"_alignFlags":42,"_originalWidth":158}],"_prefab":{"__type__":"cc.PrefabInfo","root":{"__id__":1},"asset":{"__uuid__":"f9E3S/NllC/5TspXPap7Bo"},"fileId":"d6X6BZkIhAkKl+3qtcyQq3"},"_color":{"__type__":"cc.Color","r":254,"g":68,"b":41},"_contentSize":{"__type__":"cc.Size","width":288,"height":40},"_anchorPoint":{"__type__":"cc.Vec2","y":1},"_position":{"__type__":"cc.Vec3","x":-143,"y":20},"_scale":{"__type__":"cc.Vec3","x":1,"y":1,"z":1}},{"__type__":"cc.Node","_name":"PLACEHOLDER_LABEL","_parent":{"__id__":30},"_level":2,"_components":[{"__type__":"cc.Label","node":{"__id__":34},"_srcBlendFactor":1,"_fontSize":20,"_enableWrapText":false,"_N$verticalAlign":1,"_N$fontFamily":"Microsoft YaHei","_N$overflow":1},{"__type__":"cc.Widget","node":{"__id__":34},"_alignFlags":42,"_originalWidth":158}],"_prefab":{"__type__":"cc.PrefabInfo","root":{"__id__":1},"asset":{"__uuid__":"f9E3S/NllC/5TspXPap7Bo"},"fileId":"dcK8IcLDtMhLqO11HaTO9d"},"_color":{"__type__":"cc.Color","r":187,"g":187,"b":187},"_contentSize":{"__type__":"cc.Size","width":290,"height":40},"_anchorPoint":{"__type__":"cc.Vec2","y":1},"_position":{"__type__":"cc.Vec3","x":-145,"y":20},"_scale":{"__type__":"cc.Vec3","x":1,"y":1,"z":1}},{"__type__":"cc.Node","_name":"Title","_parent":{"__id__":11},"_children":[{"__id__":36}],"_level":5,"_components":[{"__type__":"cc.Sprite","node":{"__id__":35},"_spriteFrame":{"__uuid__":"f8VAn5z9lAKL/R7GProb+K"}}],"_prefab":{"__type__":"cc.PrefabInfo","root":{"__id__":1},"asset":{"__uuid__":"f9E3S/NllC/5TspXPap7Bo"},"fileId":"feeSwEfrhKW7vGxCw5GlN7"},"_contentSize":{"__type__":"cc.Size","width":498,"height":157},"_position":{"__type__":"cc.Vec3","y":166},"_scale":{"__type__":"cc.Vec3","x":1,"y":1,"z":1}},{"__type__":"cc.Node","_name":"Label","_parent":{"__id__":35},"_level":6,"_components":[{"__type__":"cc.Label","node":{"__id__":36},"_srcBlendFactor":1,"_useOriginalSize":false,"_fontSize":28,"_N$horizontalAlign":1,"_N$verticalAlign":1,"_N$fontFamily":"Microsoft YaHei"},{"__type__":"cc.LabelOutline","node":{"__id__":36},"_color":{"__type__":"cc.Color","r":254,"g":68,"b":41},"_width":0.3},{"__type__":"cc.Widget","node":{"__id__":36},"_alignFlags":18}],"_prefab":{"__type__":"cc.PrefabInfo","root":{"__id__":1},"asset":{"__uuid__":"f9E3S/NllC/5TspXPap7Bo"},"fileId":"7fqz6eRRlOcaM8uEJc/uHE"},"_color":{"__type__":"cc.Color","r":254,"g":68,"b":41},"_contentSize":{"__type__":"cc.Size","width":0.6,"height":40},"_scale":{"__type__":"cc.Vec3","x":1,"y":1,"z":1}},{"__type__":"cc.Node","_name":"Header","_parent":{"__id__":3},"_level":4,"_components":[{"__type__":"cc.Sprite","node":{"__id__":37},"_spriteFrame":{"__uuid__":"19ymkGQ+lMYI+aif6BYrJ9"}},{"__type__":"cc.Widget","node":{"__id__":37},"_alignFlags":18,"_verticalCenter":180,"_horizontalCenter":-10}],"_prefab":{"__type__":"cc.PrefabInfo","root":{"__id__":1},"asset":{"__uuid__":"f9E3S/NllC/5TspXPap7Bo"},"fileId":"82/wHvaGVNp67mlXrdqrcJ"},"_contentSize":{"__type__":"cc.Size","width":560,"height":603},"_position":{"__type__":"cc.Vec3","x":-10,"y":180},"_scale":{"__type__":"cc.Vec3","x":1,"y":1,"z":1}},{"__type__":"cc.Node","_name":"Failed","_parent":{"__id__":1},"_children":[{"__id__":39},{"__id__":44},{"__id__":46}],"_active":false,"_level":3,"_components":[{"__type__":"cc.Widget","node":{"__id__":38},"_alignFlags":45}],"_prefab":{"__type__":"cc.PrefabInfo","root":{"__id__":1},"asset":{"__uuid__":"f9E3S/NllC/5TspXPap7Bo"},"fileId":"b3GqaQjMtE+Kf9CBmgCcHt"},"_contentSize":{"__type__":"cc.Size","width":640,"height":1013},"_scale":{"__type__":"cc.Vec3","x":1,"y":1,"z":1}},{"__type__":"cc.Node","_name":"Buttons","_parent":{"__id__":38},"_children":[{"__id__":40},{"__id__":42}],"_level":4,"_components":[{"__type__":"cc.Layout","node":{"__id__":39},"_layoutSize":{"__type__":"cc.Size","width":452,"height":200},"_resize":1,"_N$layoutType":1,"_N$spacingX":40},{"__type__":"cc.Widget","node":{"__id__":39},"_alignFlags":16,"_left":170,"_right":170,"_originalWidth":300}],"_prefab":{"__type__":"cc.PrefabInfo","root":{"__id__":1},"asset":{"__uuid__":"f9E3S/NllC/5TspXPap7Bo"},"fileId":"f2LA/hFdtJcb44ShVEuyML"},"_contentSize":{"__type__":"cc.Size","width":452,"height":200},"_scale":{"__type__":"cc.Vec3","x":1,"y":1,"z":1}},{"__type__":"cc.Node","_name":"Return","_parent":{"__id__":39},"_children":[{"__id__":41}],"_level":5,"_components":[{"__type__":"cc.Sprite","node":{"__id__":40},"_spriteFrame":{"__uuid__":"edRXsXSUVJja1zANb/8hDQ"}},{"__type__":"cc.Button","node":{"__id__":40},"transition":2,"pressedColor":{"__type__":"cc.Color","r":255,"g":255,"b":255},"clickEvents":[{"__type__":"cc.ClickEvent","target":{"__id__":1},"component":"LayerResult","handler":"btnAction","customEventData":"return"}],"_N$normalColor":{"__type__":"cc.Color","r":255,"g":255,"b":255},"_N$disabledColor":{"__type__":"cc.Color","r":255,"g":255,"b":255},"_N$normalSprite":{"__uuid__":"edRXsXSUVJja1zANb/8hDQ"},"_N$pressedSprite":{"__uuid__":"26iqIqvGxP1rGL1GKtpmX/"},"pressedSprite":{"__uuid__":"26iqIqvGxP1rGL1GKtpmX/"},"_N$hoverSprite":{"__uuid__":"edRXsXSUVJja1zANb/8hDQ"},"hoverSprite":{"__uuid__":"edRXsXSUVJja1zANb/8hDQ"},"_N$disabledSprite":{"__uuid__":"edRXsXSUVJja1zANb/8hDQ"},"_N$target":{"__id__":40}},{"__type__":"cc.Widget","node":{"__id__":40},"_alignFlags":2,"_left":200,"_right":-50,"_verticalCenter":-400,"_horizontalCenter":150,"_originalWidth":200}],"_prefab":{"__type__":"cc.PrefabInfo","root":{"__id__":1},"asset":{"__uuid__":"f9E3S/NllC/5TspXPap7Bo"},"fileId":"c3AGx1X3VGxrazzDxxH+9T"},"_contentSize":{"__type__":"cc.Size","width":206,"height":64},"_position":{"__type__":"cc.Vec3","x":-123,"y":-400},"_scale":{"__type__":"cc.Vec3","x":1,"y":1,"z":1}},{"__type__":"cc.Node","_name":"Label","_parent":{"__id__":40},"_components":[{"__type__":"cc.Label","node":{"__id__":41},"_srcBlendFactor":1,"_useOriginalSize":false,"_string":"再来一次","_N$string":"再来一次","_fontSize":26,"_enableWrapText":false,"_N$horizontalAlign":1,"_N$verticalAlign":1,"_N$fontFamily":"Microsoft YaHei","_N$overflow":1}],"_prefab":{"__type__":"cc.PrefabInfo","root":{"__id__":1},"asset":{"__uuid__":"f9E3S/NllC/5TspXPap7Bo"},"fileId":"d2DNHJ9j1I0ZiDVhUNLzeN"},"_contentSize":{"__type__":"cc.Size","width":160,"height":40},"_scale":{"__type__":"cc.Vec3","x":1,"y":1,"z":1}},{"__type__":"cc.Node","_name":"Subscribe","_parent":{"__id__":39},"_children":[{"__id__":43}],"_level":5,"_components":[{"__type__":"cc.Sprite","node":{"__id__":42},"_spriteFrame":{"__uuid__":"edRXsXSUVJja1zANb/8hDQ"}},{"__type__":"cc.Button","node":{"__id__":42},"transition":2,"pressedColor":{"__type__":"cc.Color","r":255,"g":255,"b":255},"clickEvents":[{"__type__":"cc.ClickEvent","target":{"__id__":1},"component":"LayerResult","handler":"btnAction","customEventData":"subscribe"}],"_N$normalColor":{"__type__":"cc.Color","r":255,"g":255,"b":255},"_N$disabledColor":{"__type__":"cc.Color","r":255,"g":255,"b":255},"_N$normalSprite":{"__uuid__":"edRXsXSUVJja1zANb/8hDQ"},"_N$pressedSprite":{"__uuid__":"26iqIqvGxP1rGL1GKtpmX/"},"pressedSprite":{"__uuid__":"26iqIqvGxP1rGL1GKtpmX/"},"_N$hoverSprite":{"__uuid__":"edRXsXSUVJja1zANb/8hDQ"},"hoverSprite":{"__uuid__":"edRXsXSUVJja1zANb/8hDQ"},"_N$disabledSprite":{"__uuid__":"edRXsXSUVJja1zANb/8hDQ"},"_N$target":{"__id__":42}},{"__type__":"cc.Widget","node":{"__id__":42},"_alignFlags":2,"_left":200,"_right":-50,"_verticalCenter":-400,"_horizontalCenter":150,"_originalWidth":200}],"_prefab":{"__type__":"cc.PrefabInfo","root":{"__id__":1},"asset":{"__uuid__":"f9E3S/NllC/5TspXPap7Bo"},"fileId":"c4Y8neWKNKiKyyvYrxtPXn"},"_contentSize":{"__type__":"cc.Size","width":206,"height":64},"_position":{"__type__":"cc.Vec3","x":123,"y":-400},"_scale":{"__type__":"cc.Vec3","x":1,"y":1,"z":1}},{"__type__":"cc.Node","_name":"Label","_parent":{"__id__":42},"_components":[{"__type__":"cc.Label","node":{"__id__":43},"_srcBlendFactor":1,"_useOriginalSize":false,"_string":"关注我们","_N$string":"关注我们","_fontSize":26,"_enableWrapText":false,"_N$horizontalAlign":1,"_N$verticalAlign":1,"_N$fontFamily":"Microsoft YaHei","_N$overflow":1}],"_prefab":{"__type__":"cc.PrefabInfo","root":{"__id__":1},"asset":{"__uuid__":"f9E3S/NllC/5TspXPap7Bo"},"fileId":"faUKd2IihKOJwLUYCFDniq"},"_contentSize":{"__type__":"cc.Size","width":160,"height":40},"_scale":{"__type__":"cc.Vec3","x":1,"y":1,"z":1}},{"__type__":"cc.Node","_name":"Body","_parent":{"__id__":38},"_children":[{"__id__":45}],"_level":4,"_components":[{"__type__":"cc.Widget","node":{"__id__":44},"_alignFlags":18,"_verticalCenter":-200,"_horizontalCenter":10}],"_prefab":{"__type__":"cc.PrefabInfo","root":{"__id__":1},"asset":{"__uuid__":"f9E3S/NllC/5TspXPap7Bo"},"fileId":"4eOe65LnNMfYM5R/kD9Pc4"},"_position":{"__type__":"cc.Vec3","x":10,"y":-200},"_scale":{"__type__":"cc.Vec3","x":1,"y":1,"z":1}},{"__type__":"cc.Node","_name":"Label","_parent":{"__id__":44},"_level":5,"_components":[{"__type__":"cc.Label","node":{"__id__":45},"_srcBlendFactor":1,"_useOriginalSize":false,"_string":"你和一个亿就差再来一次！","_N$string":"你和一个亿就差再来一次！","_lineHeight":80,"_N$horizontalAlign":1,"_N$verticalAlign":1,"_N$fontFamily":"Microsoft YaHei"}],"_prefab":{"__type__":"cc.PrefabInfo","root":{"__id__":1},"asset":{"__uuid__":"f9E3S/NllC/5TspXPap7Bo"},"fileId":"59qEsE2ztCy4v4Fwh9mkeb"},"_contentSize":{"__type__":"cc.Size","width":480,"height":80},"_scale":{"__type__":"cc.Vec3","x":1,"y":1,"z":1}},{"__type__":"cc.Node","_name":"Header","_parent":{"__id__":38},"_level":4,"_components":[{"__type__":"cc.Sprite","node":{"__id__":46},"_spriteFrame":{"__uuid__":"7bmL8gGx9A/KoRr32xWZOi"}},{"__type__":"cc.Widget","node":{"__id__":46},"_alignFlags":18,"_horizontalCenter":10}],"_prefab":{"__type__":"cc.PrefabInfo","root":{"__id__":1},"asset":{"__uuid__":"f9E3S/NllC/5TspXPap7Bo"},"fileId":"00Jkvx3W1PoaM12ebl1+Ss"},"_contentSize":{"__type__":"cc.Size","width":529,"height":546},"_position":{"__type__":"cc.Vec3","x":10},"_scale":{"__type__":"cc.Vec3","x":1,"y":1,"z":1}}],{"__type__":"cc.SpriteFrame","content":{"name":"default_editbox_bg","texture":"ed0hW5J5ZKBar1gflskoHO","rect":[0,0,40,40],"offset":[0,0],"originalSize":[40,40],"capInsets":[12,12,12,12]}}]